setup.cfg
setup.py
cloudvariables/__init__.py
cloudvariables/coder.py
cloudvariables.egg-info/PKG-INFO
cloudvariables.egg-info/SOURCES.txt
cloudvariables.egg-info/dependency_links.txt
cloudvariables.egg-info/not-zip-safe
cloudvariables.egg-info/top_level.txt