Metadata-Version: 2.4
Name: cloudvariables
Version: 0.1
Summary: Adds cloud variables that can be connected to using a token and password, requires a server
Author-email: zvs.developer@gmail.com
Dynamic: author-email
Dynamic: summary
